{
  "versions": [
    {
      "id": "1.7.10",
      "version": 1,
      "resources": [
        {
          "type": "VERSION",
          "url": "https://raw.githubusercontent.com/mtbarr/raw-server-data/main/1.7.10.json"
        },
        {
          "type": "FORGE_VERSION",
          "url": "https://raw.githubusercontent.com/mtbarr/raw-server-data/main/forge-1.7.10.json"
        },
        {
          "type": "SERVER",
          "url": "https://drive.usercontent.google.com/download?id=1cfburHA-xaemyF33rjvQzseBv0jndgu-&export=download&authuser=0"
        }
      ]
    }
  ]
}
